ADLStream/__init__.py
ADLStream/adlstream.py
ADLStream/data/__init__.py
ADLStream/data/base_stream_generator.py
ADLStream/data/classification_generator.py
ADLStream/data/moving_window_generator.py
ADLStream/data/preprocessing/__init__.py
ADLStream/data/preprocessing/base_preprocessor.py
ADLStream/data/preprocessing/mean_normalization_scaler.py
ADLStream/data/preprocessing/min_max_scaler.py
ADLStream/data/preprocessing/standardization_scaler.py
ADLStream/data/stream/__init__.py
ADLStream/data/stream/base_stream.py
ADLStream/data/stream/csv_file_stream.py
ADLStream/data/stream/data_stream.py
ADLStream/data/stream/fake_stream.py
ADLStream/data/stream/file_stream.py
ADLStream/data/stream/kafka_stream.py
ADLStream/data/stream/river_stream.py
ADLStream/evaluation/__init__.py
ADLStream/evaluation/base_evaluator.py
ADLStream/evaluation/interleaved_chunks.py
ADLStream/evaluation/metrics.py
ADLStream/evaluation/prequential.py
ADLStream/models/__init__.py
ADLStream/models/cnn.py
ADLStream/models/ernn.py
ADLStream/models/esn.py
ADLStream/models/gru.py
ADLStream/models/lstm.py
ADLStream/models/mlp.py
ADLStream/models/model_factory.py
ADLStream/models/tcn.py
ADLStream/models/transformer.py
ADLStream/utils/__init__.py
ADLStream/utils/plot_utils.py
ADLStream/utils/test_utils.py
ADLStream-0.1.5.dist-info/LICENSE.md
ADLStream-0.1.5.dist-info/METADATA
ADLStream-0.1.5.dist-info/WHEEL
ADLStream-0.1.5.dist-info/top_level.txt
ADLStream-0.1.5.dist-info/RECORD
