Metadata-Version: 2.1
Name: ADLStream
Version: 0.1.5
Summary: ADLStream is a novel asynchronous dual-pipeline deep learning framework for data stream mining
Home-page: https://adlstream.readthedocs.io
Author: Pedro Lara-Benítez & Manuel Carranza-García
Author-email: plbenitez@us.es
License: MIT
Project-URL: Download, https://github.com/pedrolarben/ADLStream/tags
Project-URL: API Documentation, https://adlstream.readthedocs.io/API/overview/
Project-URL: Paper, https://doi.org/10.3233/ICA-200617
Platform: UNKNOWN
Classifier: Development Status :: 3 - Alpha
Classifier: Environment :: GPU :: NVIDIA CUDA :: 11.2
Classifier: Programming Language :: Python
Classifier: Programming Language :: Python :: 3 :: Only
Classifier: Programming Language :: Python :: 3
Classifier: Programming Language :: Python :: 3.6
Classifier: Programming Language :: Python :: 3.7
Classifier: Programming Language :: Python :: 3.8
Classifier: Programming Language :: Python :: 3.9
Classifier: Intended Audience :: Developers
Classifier: Intended Audience :: Education
Classifier: Intended Audience :: Science/Research
Classifier: License :: OSI Approved :: MIT License
Classifier: Topic :: Scientific/Engineering
Classifier: Topic :: Scientific/Engineering :: Artificial Intelligence
Classifier: Topic :: Scientific/Engineering :: Information Analysis
Classifier: Topic :: Software Development
Classifier: Topic :: Software Development :: Libraries
Classifier: Topic :: Software Development :: Libraries :: Python Modules
License-File: LICENSE.md
Requires-Dist: numpy
Requires-Dist: tensorflow (>=2.1.0)
Requires-Dist: tensorflow-addons (>=0.11.0)
Requires-Dist: keras-tcn
Requires-Dist: matplotlib
Requires-Dist: scikit-learn
Requires-Dist: kafka-python
